synchronous_fifo.v
module sync_fifo (clk,reset,wr_data,wr_en,full,rd_data,rd_en,empty) ;

input clk,reset,wr_en,rd_en ;
input [7:0] wr_data;
output reg [7:0] rd_data ;
output full,empty ;

reg [6:0] wr_ptr,rd_ptr ;
reg [6:0] count ;
reg [7:0] mem [0:63] ;  // Memory FIFO

assign full = (count == 64) ; // this checks for the status flag
assign empty = (count == 0) ;
 
always @ (posedge clk)     // this always block manages fifo counter
    begin
        if (reset)
            count <= 0 ;
        else if ((!full && wr_en) && (!empty && rd_en))  // if read and write is done simultaneously at the same posedge of clk then effectively the count remains same as before
            count <= count ;
        else if (!full && wr_en) 
            count <= count + 1 ;
        else if (!empty && rd_en)
            count <= count -1 ;
        else 
            count <= count ;  
    end

// ***** READ OPERATION ***** 
always @ (posedge clk)
    begin
        if (reset)
            rd_data <= 0 ;
        else if (!empty && rd_en)
            rd_data <= mem[rd_ptr] ;
        else 
            rd_data <= rd_data ;    
    end

// ***** WRITE OPERATION ***** 
always @ (posedge clk)
    begin 
        if (!full && wr_en)
            mem[wr_ptr] <= wr_data ;
        else 
            mem[wr_ptr] <= mem[wr_ptr] ;
    end

// ***** MOVEMENT OF POINTERS *****
always @ (posedge clk)
    begin
        if (reset)
            begin
                wr_ptr <= 0 ;
                rd_ptr <= 0 ;
            end
        else
            begin
                if (!full && wr_en)    // write pointer
                    wr_ptr <= (wr_ptr == 63) ? 0 : wr_ptr + 1 ;
                else 
                    wr_ptr <= wr_ptr ;
                
                if (!empty && rd_en)  // read pointer
                    rd_ptr <= (rd_ptr == 63) ? 0 : rd_ptr + 1 ;
                else
                    rd_ptr <= rd_ptr ;    

            end    
    end
endmodule

test.v
module test_bench ;

reg clk,reset,wr_en,rd_en ;
reg [7:0] wr_data;
wire [7:0] rd_data ;
wire full,empty ;

sync_fifo FIFO (clk,reset,wr_data,wr_en,full,rd_data,rd_en,empty) ;

initial
    begin
        clk = 1'b0 ;
        forever 
        #5 clk = ~ clk ;
    end

initial
    begin
        $dumpfile ("Sync_FIFO.vcd") ;
        $dumpvars (0,test_bench) ;
        // $monitor ("mem[%d]",FIFO.mem[0] ) ;
        $monitor("time=%0t, rd_data=%b, empty=%b, full=%b", $time, rd_data, empty, full);



        reset = 1'b1 ;
        #12 ;
        reset = 1'b0 ;

        wr_en = 1 ;

        wr_data = 8'b10010001 ;
        #2 ;
        #7 wr_data = 8'b01011011 ;
        #2 $display("mem[0] = %b", FIFO.mem[0]);

        #7 wr_data = 8'b11111011 ;
        #2 $display("mem[1] = %b", FIFO.mem[1]);

        #12 ;
        $display("mem[2] = %b", FIFO.mem[2]) ;
        wr_en = 0 ;
        rd_en = 1 ;
        #10 ;

        #2 ;

        #200 $finish ;
    end
endmodule

Sync_FIFO.vcd
$date
	Sat Jun 21 12:38:06 2025
$end
$version
	Icarus Verilog
$end
$timescale
	1s
$end
$scope module test_bench $end
$var wire 8 ! rd_data [7:0] $end
$var wire 1 " full $end
$var wire 1 # empty $end
$var reg 1 $ clk $end
$var reg 1 % rd_en $end
$var reg 1 & reset $end
$var reg 8 ' wr_data [7:0] $end
$var reg 1 ( wr_en $end
$scope module FIFO $end
$var wire 1 $ clk $end
$var wire 1 % rd_en $end
$var wire 1 & reset $end
$var wire 8 ) wr_data [7:0] $end
$var wire 1 ( wr_en $end
$var wire 1 " full $end
$var wire 1 # empty $end
$var reg 7 * count [6:0] $end
$var reg 8 + rd_data [7:0] $end
$var reg 7 , rd_ptr [6:0] $end
$var reg 7 - wr_ptr [6:0] $end
$upscope $end
$upscope $end
$enddefinitions $end
$comment Show the parameter values. $end
$dumpall
$end
#0
$dumpvars
bx -
bx ,
bx +
bx *
bx )
x(
bx '
1&
x%
0$
x#
x"
bx !
$end
#5
0"
1#
b0 *
b0 !
b0 +
b0 ,
b0 -
1$
#10
0$
#12
b10010001 '
b10010001 )
1(
0&
#15
b1 -
0#
b1 *
1$
#20
0$
#21
b1011011 '
b1011011 )
#25
b10 *
b10 -
1$
#30
0$
b11111011 '
b11111011 )
#35
b11 -
b11 *
1$
#40
0$
#44
1%
0(
#45
b10 *
b10010001 !
b10010001 +
b1 ,
1$
#50
0$
#55
b10 ,
b1011011 !
b1011011 +
b1 *
1$
#60
0$
#65
1#
b0 *
b11111011 !
b11111011 +
b11 ,
1$
